star_openapi_scalar/__init__.py
star_openapi_scalar/__version__.py
star_openapi_scalar/plugins.py
star_openapi_scalar/templates/__init__.py
star_openapi_scalar/templates/scalar/images/scalar.svg
star_openapi_scalar/templates/scalar/js/scalar.standalone.js
star_openapi_scalar-1.44.6.dist-info/METADATA
star_openapi_scalar-1.44.6.dist-info/WHEEL
star_openapi_scalar-1.44.6.dist-info/entry_points.txt
star_openapi_scalar-1.44.6.dist-info/RECORD
