Metadata-Version: 2.4
Name: star-openapi-scalar
Version: 1.44.6
Summary: Provide Scalar UI for star-openapi.
Project-URL: Homepage, https://github.com/luolingchun/star-openapi-plugins/tree/master/star-openapi-scalar
Project-URL: Documentation, https://luolingchun.github.io/star-openapi/latest/Usage/UI_Templates/
Maintainer-email: llc <luolingchun@outlook.com>
License: MIT
Classifier: Development Status :: 5 - Production/Stable
Classifier: Environment :: Web Environment
Classifier: Intended Audience :: Developers
Classifier: License :: OSI Approved :: MIT License
Classifier: Operating System :: OS Independent
Classifier: Programming Language :: Python
Classifier: Programming Language :: Python :: 3
Classifier: Programming Language :: Python :: 3 :: Only
Requires-Python: >=3.8
Requires-Dist: star-openapi
